{
  "project_info": {
    "project_number": "1008639778895",
    "project_id": "churchsnap-d8fe6",
    "storage_bucket": "churchsnap-d8fe6.firebasestorage.app"
  },
  "client": [
    {
      "client_info": {
        "mobilesdk_app_id": "1:1008639778895:android:6e130ffd69747ad7baca3a",
        "android_client_info": {
          "package_name": "com.churchsnap.app"
        }
      },
      "oauth_client": [],
      "api_key": [
        {
          "current_key": "AIzaSyC3XhBm9P-CzaLFXZbUjlOYr64dDo8CFOo"
        }
      ],
      "services": {
        "appinvite_service": {
          "other_platform_oauth_client": []
        }
      }
    },
    {
      "client_info": {
        "mobilesdk_app_id": "1:1008639778895:android:ba08ba294736ba53baca3a",
        "android_client_info": {
          "package_name": "com.example.churchsnap"
        }
      },
      "oauth_client": [],
      "api_key": [
        {
          "current_key": "AIzaSyC3XhBm9P-CzaLFXZbUjlOYr64dDo8CFOo"
        }
      ],
      "services": {
        "appinvite_service": {
          "other_platform_oauth_client": []
        }
      }
    }
  ],
  "configuration_version": "1"
}